ValWrap/__init__.py
ValWrap/requests.py
ValWrap-0.10.1.dist-info/METADATA
ValWrap-0.10.1.dist-info/WHEEL
ValWrap-0.10.1.dist-info/top_level.txt
ValWrap-0.10.1.dist-info/RECORD
